LICENSE
README.md
vcdiff_decoder/__init__.py
vcdiff_decoder/addresscache.py
vcdiff_decoder/adler32.py
vcdiff_decoder/codetable.py
vcdiff_decoder/decoder.py
vcdiff_decoder/exceptions.py
vcdiff_decoder/types.py
vcdiff_decoder/varint.py
vcdiff_decoder-0.1.0.dist-info/LICENSE
vcdiff_decoder-0.1.0.dist-info/METADATA
vcdiff_decoder-0.1.0.dist-info/WHEEL
vcdiff_decoder-0.1.0.dist-info/RECORD
